mocka/__init__.py
mocka/mocka.py
mocka-0.0.8.dist-info/DESCRIPTION.rst
mocka-0.0.8.dist-info/METADATA
mocka-0.0.8.dist-info/RECORD
mocka-0.0.8.dist-info/WHEEL
mocka-0.0.8.dist-info/entry_points.txt
mocka-0.0.8.dist-info/metadata.json
mocka-0.0.8.dist-info/top_level.txt
tests/__init__.py
tests/run_test.py
